[
  {
    "first": {
      "x": 30.0105,
      "y": 117.866
    },
    "second": {
      "x": 19.3657,
      "y": 14.3835
    }
  },
  {
    "first": {
      "x": 30.0105,
      "y": 117.866
    },
    "second": {
      "x": 19.3657,
      "y": 14.3835
    }
  },
  {
    "first": {
      "x": 480.387,
      "y": 124.787
    },
    "second": {
      "x": 452.641,
      "y": 139.003
    }
  },
  {
    "first": {
      "x": 480.387,
      "y": 124.787
    },
    "second": {
      "x": 452.641,
      "y": 139.003
    }
  },
  {
    "first": {
      "x": 328.594,
      "y": 134.304
    },
    "second": {
      "x": 276.558,
      "y": 186.951
    }
  },
  {
    "first": {
      "x": 339.625,
      "y": 136.32
    },
    "second": {
      "x": 285.55,
      "y": 187.601
    }
  },
  {
    "first": {
      "x": 470.334,
      "y": 137.179
    },
    "second": {
      "x": 443.342,
      "y": 154.221
    }
  },
  {
    "first": {
      "x": 369.396,
      "y": 140.081
    },
    "second": {
      "x": 337.161,
      "y": 179.078
    }
  },
  {
    "first": {
      "x": 486.232,
      "y": 140.298
    },
    "second": {
      "x": 463.114,
      "y": 153.271
    }
  },
  {
    "first": {
      "x": 399.548,
      "y": 164.82
    },
    "second": {
      "x": 365.981,
      "y": 195.684
    }
  },
  {
    "first": {
      "x": 399.548,
      "y": 164.82
    },
    "second": {
      "x": 365.981,
      "y": 195.684
    }
  },
  {
    "first": {
      "x": 460.209,
      "y": 174.968
    },
    "second": {
      "x": 430.446,
      "y": 193.654
    }
  },
  {
    "first": {
      "x": 594.051,
      "y": 195.838
    },
    "second": {
      "x": 599.137,
      "y": 187.503
    }
  },
  {
    "first": {
      "x": 594.051,
      "y": 195.838
    },
    "second": {
      "x": 599.137,
      "y": 187.503
    }
  },
  {
    "first": {
      "x": 482.316,
      "y": 233.165
    },
    "second": {
      "x": 454.505,
      "y": 248.31
    }
  },
  {
    "first": {
      "x": 490.213,
      "y": 236.735
    },
    "second": {
      "x": 465.276,
      "y": 250.795
    }
  },
  {
    "first": {
      "x": 490.213,
      "y": 236.735
    },
    "second": {
      "x": 465.276,
      "y": 250.795
    }
  },
  {
    "first": {
      "x": 568.041,
      "y": 260.328
    },
    "second": {
      "x": 571.452,
      "y": 262.955
    }
  },
  {
    "first": {
      "x": 568.041,
      "y": 260.328
    },
    "second": {
      "x": 571.452,
      "y": 262.955
    }
  },
  {
    "first": {
      "x": 420.836,
      "y": 275.657
    },
    "second": {
      "x": 564.837,
      "y": 295.871
    }
  },
  {
    "first": {
      "x": 427.837,
      "y": 276.1
    },
    "second": {
      "x": 525.117,
      "y": 228.11
    }
  },
  {
    "first": {
      "x": 432.77,
      "y": 375.35
    },
    "second": {
      "x": 227.062,
      "y": 401.532
    }
  },
  {
    "first": {
      "x": 456.0,
      "y": 389.159
    },
    "second": {
      "x": 251.28,
      "y": 411.811
    }
  },
  {
    "first": {
      "x": 456.0,
      "y": 389.159
    },
    "second": {
      "x": 251.28,
      "y": 411.811
    }
  },
  {
    "first": {
      "x": 474.994,
      "y": 398.054
    },
    "second": {
      "x": 266.668,
      "y": 421.542
    }
  },
  {
    "first": {
      "x": 480.211,
      "y": 125.816
    },
    "second": {
      "x": 452.638,
      "y": 139.863
    }
  },
  {
    "first": {
      "x": 339.254,
      "y": 135.869
    },
    "second": {
      "x": 285.436,
      "y": 186.968
    }
  },
  {
    "first": {
      "x": 369.713,
      "y": 139.841
    },
    "second": {
      "x": 337.161,
      "y": 179.078
    }
  },
  {
    "first": {
      "x": 486.518,
      "y": 141.588
    },
    "second": {
      "x": 463.543,
      "y": 153.621
    }
  },
  {
    "first": {
      "x": 399.02,
      "y": 155.637
    },
    "second": {
      "x": 365.107,
      "y": 187.745
    }
  },
  {
    "first": {
      "x": 399.02,
      "y": 155.637
    },
    "second": {
      "x": 365.107,
      "y": 187.745
    }
  },
  {
    "first": {
      "x": 405.469,
      "y": 165.475
    },
    "second": {
      "x": 544.141,
      "y": 194.092
    }
  },
  {
    "first": {
      "x": 441.397,
      "y": 172.284
    },
    "second": {
      "x": 408.922,
      "y": 194.313
    }
  },
  {
    "first": {
      "x": 489.824,
      "y": 236.135
    },
    "second": {
      "x": 464.915,
      "y": 250.448
    }
  },
  {
    "first": {
      "x": 489.824,
      "y": 236.135
    },
    "second": {
      "x": 464.915,
      "y": 250.448
    }
  },
  {
    "first": {
      "x": 382.627,
      "y": 401.943
    },
    "second": {
      "x": 100.718,
      "y": 424.57
    }
  },
  {
    "first": {
      "x": 30.0208,
      "y": 117.831
    },
    "second": {
      "x": 19.1249,
      "y": 14.7329
    }
  },
  {
    "first": {
      "x": 30.0208,
      "y": 117.831
    },
    "second": {
      "x": 19.1249,
      "y": 14.7329
    }
  },
  {
    "first": {
      "x": 256.601,
      "y": 127.801
    },
    "second": {
      "x": 236.6,
      "y": 190.021
    }
  },
  {
    "first": {
      "x": 479.394,
      "y": 128.673
    },
    "second": {
      "x": 452.839,
      "y": 141.027
    }
  },
  {
    "first": {
      "x": 328.958,
      "y": 133.221
    },
    "second": {
      "x": 276.691,
      "y": 186.215
    }
  },
  {
    "first": {
      "x": 339.039,
      "y": 135.124
    },
    "second": {
      "x": 285.436,
      "y": 186.968
    }
  },
  {
    "first": {
      "x": 243.928,
      "y": 136.565
    },
    "second": {
      "x": 227.108,
      "y": 199.285
    }
  },
  {
    "first": {
      "x": 470.3,
      "y": 137.196
    },
    "second": {
      "x": 443.93,
      "y": 153.822
    }
  },
  {
    "first": {
      "x": 369.624,
      "y": 140.604
    },
    "second": {
      "x": 337.269,
      "y": 179.257
    }
  },
  {
    "first": {
      "x": 399.48,
      "y": 156.113
    },
    "second": {
      "x": 365.908,
      "y": 188.862
    }
  },
  {
    "first": {
      "x": 399.48,
      "y": 156.113
    },
    "second": {
      "x": 365.908,
      "y": 188.862
    }
  },
  {
    "first": {
      "x": 399.48,
      "y": 156.113
    },
    "second": {
      "x": 365.908,
      "y": 188.862
    }
  },
  {
    "first": {
      "x": 387.56,
      "y": 161.9
    },
    "second": {
      "x": 477.741,
      "y": 192.913
    }
  },
  {
    "first": {
      "x": 403.417,
      "y": 164.195
    },
    "second": {
      "x": 540.943,
      "y": 193.439
    }
  },
  {
    "first": {
      "x": 473.787,
      "y": 233.707
    },
    "second": {
      "x": 443.601,
      "y": 250.738
    }
  },
  {
    "first": {
      "x": 473.787,
      "y": 233.707
    },
    "second": {
      "x": 444.27,
      "y": 250.227
    }
  },
  {
    "first": {
      "x": 566.963,
      "y": 260.563
    },
    "second": {
      "x": 570.747,
      "y": 263.576
    }
  },
  {
    "first": {
      "x": 427.382,
      "y": 275.709
    },
    "second": {
      "x": 524.688,
      "y": 228.065
    }
  },
  {
    "first": {
      "x": 429.508,
      "y": 370.118
    },
    "second": {
      "x": 224.142,
      "y": 397.46
    }
  },
  {
    "first": {
      "x": 429.508,
      "y": 370.118
    },
    "second": {
      "x": 223.379,
      "y": 397.22
    }
  },
  {
    "first": {
      "x": 468.304,
      "y": 384.085
    },
    "second": {
      "x": 260.95,
      "y": 409.309
    }
  },
  {
    "first": {
      "x": 382.472,
      "y": 402.58
    },
    "second": {
      "x": 100.774,
      "y": 424.33
    }
  },
  {
    "first": {
      "x": 348.579,
      "y": 418.72
    },
    "second": {
      "x": 74.4737,
      "y": 435.47
    }
  },
  {
    "first": {
      "x": 387.127,
      "y": 423.137
    },
    "second": {
      "x": 101.964,
      "y": 432.966
    }
  },
  {
    "first": {
      "x": 329.119,
      "y": 125.131
    },
    "second": {
      "x": 275.828,
      "y": 180.461
    }
  },
  {
    "first": {
      "x": 253.237,
      "y": 135.864
    },
    "second": {
      "x": 234.487,
      "y": 197.864
    }
  },
  {
    "first": {
      "x": 471.01,
      "y": 137.128
    },
    "second": {
      "x": 443.915,
      "y": 154.481
    }
  },
  {
    "first": {
      "x": 471.01,
      "y": 137.128
    },
    "second": {
      "x": 443.915,
      "y": 154.481
    }
  },
  {
    "first": {
      "x": 369.38,
      "y": 140.377
    },
    "second": {
      "x": 337.269,
      "y": 179.257
    }
  },
  {
    "first": {
      "x": 387.411,
      "y": 161.746
    },
    "second": {
      "x": 477.281,
      "y": 193.304
    }
  },
  {
    "first": {
      "x": 387.411,
      "y": 161.746
    },
    "second": {
      "x": 477.281,
      "y": 193.304
    }
  },
  {
    "first": {
      "x": 460.857,
      "y": 175.532
    },
    "second": {
      "x": 431.198,
      "y": 194.459
    }
  },
  {
    "first": {
      "x": 595.08,
      "y": 196.648
    },
    "second": {
      "x": 599.579,
      "y": 187.793
    }
  },
  {
    "first": {
      "x": 496.757,
      "y": 216.511
    },
    "second": {
      "x": 475.84,
      "y": 228.255
    }
  },
  {
    "first": {
      "x": 427.137,
      "y": 275.55
    },
    "second": {
      "x": 524.494,
      "y": 227.882
    }
  },
  {
    "first": {
      "x": 364.69,
      "y": 382.997
    },
    "second": {
      "x": 86.9137,
      "y": 410.268
    }
  },
  {
    "first": {
      "x": 364.69,
      "y": 382.997
    },
    "second": {
      "x": 86.7115,
      "y": 410.578
    }
  },
  {
    "first": {
      "x": 360.822,
      "y": 399.027
    },
    "second": {
      "x": 82.7901,
      "y": 421.498
    }
  },
  {
    "first": {
      "x": 382.152,
      "y": 403.512
    },
    "second": {
      "x": 100.289,
      "y": 425.17
    }
  },
  {
    "first": {
      "x": 366.807,
      "y": 410.537
    },
    "second": {
      "x": 86.8348,
      "y": 430.135
    }
  },
  {
    "first": {
      "x": 366.807,
      "y": 410.537
    },
    "second": {
      "x": 86.8348,
      "y": 430.135
    }
  },
  {
    "first": {
      "x": 252.714,
      "y": 134.716
    },
    "second": {
      "x": 233.901,
      "y": 197.126
    }
  },
  {
    "first": {
      "x": 470.772,
      "y": 139.537
    },
    "second": {
      "x": 443.678,
      "y": 155.547
    }
  },
  {
    "first": {
      "x": 470.772,
      "y": 139.537
    },
    "second": {
      "x": 443.053,
      "y": 158.001
    }
  },
  {
    "first": {
      "x": 485.204,
      "y": 142.396
    },
    "second": {
      "x": 463.353,
      "y": 155.189
    }
  },
  {
    "first": {
      "x": 485.204,
      "y": 142.396
    },
    "second": {
      "x": 463.353,
      "y": 155.189
    }
  },
  {
    "first": {
      "x": 387.326,
      "y": 161.879
    },
    "second": {
      "x": 477.322,
      "y": 193.164
    }
  },
  {
    "first": {
      "x": 487.73,
      "y": 181.186
    },
    "second": {
      "x": 462.427,
      "y": 194.48
    }
  },
  {
    "first": {
      "x": 487.73,
      "y": 181.186
    },
    "second": {
      "x": 462.427,
      "y": 194.48
    }
  },
  {
    "first": {
      "x": 594.404,
      "y": 196.578
    },
    "second": {
      "x": 599.487,
      "y": 188.048
    }
  },
  {
    "first": {
      "x": 594.404,
      "y": 196.578
    },
    "second": {
      "x": 599.487,
      "y": 188.048
    }
  },
  {
    "first": {
      "x": 560.673,
      "y": 259.69
    },
    "second": {
      "x": 560.244,
      "y": 264.869
    }
  },
  {
    "first": {
      "x": 426.904,
      "y": 275.464
    },
    "second": {
      "x": 524.203,
      "y": 227.563
    }
  },
  {
    "first": {
      "x": 381.348,
      "y": 404.206
    },
    "second": {
      "x": 99.3699,
      "y": 425.623
    }
  },
  {
    "first": {
      "x": 332.059,
      "y": 131.685
    },
    "second": {
      "x": 277.862,
      "y": 185.105
    }
  },
  {
    "first": {
      "x": 332.059,
      "y": 131.685
    },
    "second": {
      "x": 279.465,
      "y": 185.064
    }
  },
  {
    "first": {
      "x": 487.468,
      "y": 144.413
    },
    "second": {
      "x": 464.122,
      "y": 157.217
    }
  },
  {
    "first": {
      "x": 487.468,
      "y": 144.413
    },
    "second": {
      "x": 464.122,
      "y": 157.217
    }
  },
  {
    "first": {
      "x": 400.032,
      "y": 162.867
    },
    "second": {
      "x": 367.444,
      "y": 195.279
    }
  },
  {
    "first": {
      "x": 400.032,
      "y": 162.867
    },
    "second": {
      "x": 367.444,
      "y": 195.279
    }
  },
  {
    "first": {
      "x": 488.181,
      "y": 181.148
    },
    "second": {
      "x": 462.157,
      "y": 193.767
    }
  },
  {
    "first": {
      "x": 488.181,
      "y": 181.148
    },
    "second": {
      "x": 462.157,
      "y": 193.767
    }
  },
  {
    "first": {
      "x": 488.181,
      "y": 181.148
    },
    "second": {
      "x": 462.157,
      "y": 193.767
    }
  },
  {
    "first": {
      "x": 596.446,
      "y": 196.769
    },
    "second": {
      "x": 601.101,
      "y": 188.306
    }
  },
  {
    "first": {
      "x": 596.446,
      "y": 196.769
    },
    "second": {
      "x": 601.101,
      "y": 188.306
    }
  },
  {
    "first": {
      "x": 561.368,
      "y": 260.124
    },
    "second": {
      "x": 561.313,
      "y": 264.873
    }
  },
  {
    "first": {
      "x": 454.527,
      "y": 301.943
    },
    "second": {
      "x": 420.491,
      "y": 317.411
    }
  },
  {
    "first": {
      "x": 364.971,
      "y": 385.552
    },
    "second": {
      "x": 86.5189,
      "y": 411.516
    }
  },
  {
    "first": {
      "x": 329.333,
      "y": 132.249
    },
    "second": {
      "x": 277.862,
      "y": 185.105
    }
  },
  {
    "first": {
      "x": 329.333,
      "y": 132.249
    },
    "second": {
      "x": 277.862,
      "y": 185.105
    }
  },
  {
    "first": {
      "x": 245.119,
      "y": 136.117
    },
    "second": {
      "x": 227.437,
      "y": 199.08
    }
  },
  {
    "first": {
      "x": 561.888,
      "y": 260.456
    },
    "second": {
      "x": 562.872,
      "y": 265.938
    }
  },
  {
    "first": {
      "x": 455.932,
      "y": 302.645
    },
    "second": {
      "x": 420.491,
      "y": 317.411
    }
  },
  {
    "first": {
      "x": 364.743,
      "y": 368.829
    },
    "second": {
      "x": 89.2988,
      "y": 397.256
    }
  },
  {
    "first": {
      "x": 421.525,
      "y": 273.843
    },
    "second": {
      "x": 562.919,
      "y": 293.157
    }
  },
  {
    "first": {
      "x": 458.511,
      "y": 302.082
    },
    "second": {
      "x": 422.454,
      "y": 317.377
    }
  },
  {
    "first": {
      "x": 458.511,
      "y": 302.082
    },
    "second": {
      "x": 422.454,
      "y": 317.377
    }
  },
  {
    "first": {
      "x": 513.275,
      "y": 190.769
    },
    "second": {
      "x": 495.952,
      "y": 201.792
    }
  },
  {
    "first": {
      "x": 513.275,
      "y": 190.769
    },
    "second": {
      "x": 495.952,
      "y": 201.792
    }
  },
  {
    "first": {
      "x": 468.657,
      "y": 246.273
    },
    "second": {
      "x": 435.364,
      "y": 265.067
    }
  }
]